tvDatafeed/__init__.py
tvDatafeed/consumer.py
tvDatafeed/datafeed.py
tvDatafeed/main.py
tvDatafeed/seis.py
replicats_tvdatafeed-0.1.0.dist-info/LICENSE
replicats_tvdatafeed-0.1.0.dist-info/METADATA
replicats_tvdatafeed-0.1.0.dist-info/WHEEL
replicats_tvdatafeed-0.1.0.dist-info/top_level.txt
replicats_tvdatafeed-0.1.0.dist-info/RECORD
